crawling_gagip/__init__.py
crawling_gagip/driver.py
crawling_gagip-0.0.5.dist-info/METADATA
crawling_gagip-0.0.5.dist-info/WHEEL
crawling_gagip-0.0.5.dist-info/top_level.txt
crawling_gagip-0.0.5.dist-info/RECORD
