Metadata-Version: 2.1
Name: crawling-gagip
Version: 0.0.5
Summary: crawling
Home-page: https://github.com/gagip/crawling-gagip
Author: gagip
Author-email: y02645@gmail.com
Requires-Python: >=3.8
